youtool/__init__.py
youtool/utils.py
youtool-0.2.0.dist-info/LICENSE
youtool-0.2.0.dist-info/METADATA
youtool-0.2.0.dist-info/WHEEL
youtool-0.2.0.dist-info/top_level.txt
youtool-0.2.0.dist-info/RECORD
