Metadata-Version: 2.1
Name: youtool
Version: 0.2.0
Summary: Easy-to-use library to access YouTube Data API v3 in bulk operations
Home-page: https://github.com/PythonicCafe/youtool/
Author: Álvaro Justen
Author-email: alvarojusten@gmail.com
License: GNU Lesser General Public License v3 (LGPLv3)
Keywords: youtube api data videos
Classifier: Intended Audience :: Developers
Classifier: License :: OSI Approved :: GNU Lesser General Public License v3 (LGPLv3)
Classifier: Operating System :: OS Independent
Classifier: Programming Language :: Python
Classifier: Programming Language :: Python :: 3
Classifier: Programming Language :: Python :: 3 :: Only
Classifier: Topic :: Internet :: WWW/HTTP
Requires-Python: >=3.7
Provides-Extra: cli
Provides-Extra: dev
Provides-Extra: transcription
Provides-Extra: livechat
License-File: LICENSE
